passman/__init__.py
passman/cli.py
passman/errors.py
passman/passman.py
python_passman-1.0.1.dist-info/LICENSE
python_passman-1.0.1.dist-info/METADATA
python_passman-1.0.1.dist-info/WHEEL
python_passman-1.0.1.dist-info/entry_points.txt
python_passman-1.0.1.dist-info/top_level.txt
python_passman-1.0.1.dist-info/RECORD
