Metadata-Version: 2.1
Name: python-passman
Version: 1.0.1
Summary: Terminal password manager in Python
Home-page: https://github.com/profility/passman
Author: profility
Author-email: contact@profility.slmail.me
License-File: LICENSE
Requires-Dist: typer
Requires-Dist: python-gnupg
